[
    {
        "name": "SanDisk Ultra 128GB SDXC UHS-I Memory Card up to 80MB/s",
        "price": "45.89",
        "description": "Ultra-fast cards (2) to take better pictures and Full HD videos (1) with your compact to mid-range point-and-shoot cameras and camcorders...",
        "ratings": 4.5,
        "images": [
            {
                "public_id": "products/sandisk_card",
                "url": "https://images.unsplash.com/photo-1626810140232-a39284201886?fit=crop&w=400&h=400&q=80"
            }
        ],
        "category": "Electronics",
        "seller": "Ebay",
        "stock": 50,
        "numOfReviews": 32,
        "reviews": []
    },
    {
        "name": "Bose QuietComfort 35 II Wireless Bluetooth Headphones",
        "price": "299.00 ",
        "description": "That’s the power of Bose QuietComfort 35 wireless headphones II. Put them on and get closer to what you’re most passionate about...",
        "ratings": 4.5,
        "images": [
            {
                "public_id": "products/bose_qc35ii_headphones",
                "url": "https://images.unsplash.com/photo-1546435035-ad69485b0185?fit=crop&w=400&h=400&q=80"
            }
        ],
        "category": "Headphones",
        "seller": "Amazon",
        "stock": 11,
        "numOfReviews": 112,
        "reviews": []
    },
    {
        "name": "Apple MacBook Air (13-inch, 8GB RAM, 256GB SSD Storage) - Space Gray ",
        "price": "949.99",
        "description": "Stunning 13.3-inch Retina display with True Tone technology, Backlit Magic Keyboard and Touch ID...",
        "ratings": 4.9,
        "images": [
            {
                "public_id": "products/macbook_air",
                "url": "https://images.unsplash.com/photo-1537498425277-c283d32ef9db?fit=crop&w=400&h=400&q=80"
            }
        ],
        "category": "Laptops",
        "seller": "Amazon",
        "stock": 0,
        "numOfReviews": 56,
        "reviews": []
    },
    
    {
        "name": "Táo Fuji Nhật Bản (Túi 1kg)",
        "price": "125.00",
        "description": "Táo Fuji nhập khẩu từ Nhật, giòn, ngọt, thơm tự nhiên. Thích hợp ăn sống hoặc làm salad.",
        "ratings": 5,
        "images": [
            {
                "public_id": "products/fuji_apple",
                "url": "https://images.unsplash.com/photo-1619546815777-6745f4705504?fit=crop&w=400&h=400&q=80"
            }
        ],
        "category": "Rau-Củ-Trái cây",
        "seller": "FreshFarm VN",
        "stock": 300,
        "numOfReviews": 15,
        "reviews": []
    },
    {
        "name": "Bông Cải Xanh Hữu Cơ (500g)",
        "price": "45.00",
        "description": "Bông cải xanh (Súp lơ xanh) hữu cơ, tươi sạch, giàu Vitamin C và K. Lý tưởng cho các món hấp hoặc xào.",
        "ratings": 4.8,
        "images": [
            {
                "public_id": "products/organic_broccoli",
                "url": "https://images.unsplash.com/photo-1581451815121-82782e4f0a0c?fit=crop&w=400&h=400&q=80"
            }
        ],
        "category": "Rau-Củ-Trái cây",
        "seller": "GreenFoods",
        "stock": 150,
        "numOfReviews": 5,
        "reviews": []
    },
    {
        "name": "Thịt Ba Chỉ Heo Tươi (500g)",
        "price": "89.50",
        "description": "Thịt ba chỉ heo tươi, đã qua kiểm dịch, thích hợp cho các món kho, luộc hoặc nướng.",
        "ratings": 4.6,
        "images": [
            {
                "public_id": "products/pork_belly",
                "url": "https://images.unsplash.com/photo-1565597951664-966504a74284?fit=crop&w=400&h=400&q=80"
            }
        ],
        "category": "Thịt-Trứng-Hải sản",
        "seller": "MeatMaster",
        "stock": 100,
        "numOfReviews": 40,
        "reviews": []
    },
    {
        "name": "Tôm Sú Đông Lạnh (Size L, 1kg)",
        "price": "350.00",
        "description": "Tôm sú tươi, cấp đông ngay sau khi đánh bắt, giữ nguyên độ ngọt và chất dinh dưỡng.",
        "ratings": 4.9,
        "images": [
            {
                "public_id": "products/frozen_shrimp",
                "url": "https://images.unsplash.com/photo-1582046808759-4f762a4d9302?fit=crop&w=400&h=400&q=80"
            }
        ],
        "category": "Thịt-Trứng-Hải sản",
        "seller": "OceanDelight",
        "stock": 80,
        "numOfReviews": 25,
        "reviews": []
    },
    {
        "name": "Xúc Xích Heo Xông Khói Tiệt Trùng (500g)",
        "price": "72.00",
        "description": "Xúc xích xông khói theo công nghệ Đức, chế biến sẵn, dùng ngay hoặc chiên nướng.",
        "ratings": 4.3,
        "images": [
            {
                "public_id": "products/smoked_sausage",
                "url": "https://images.unsplash.com/photo-1542475727-463e26487955?fit=crop&w=400&h=400&q=80"
            }
        ],
        "category": "Thực phẩm chế biến",
        "seller": "Gourmet Foods",
        "stock": 220,
        "numOfReviews": 18,
        "reviews": []
    },
    {
        "name": "Kem Vani Hộp Lớn (1 Lít)",
        "price": "110.00",
        "description": "Kem hương Vani tự nhiên, béo ngậy, giải khát tuyệt vời.",
        "ratings": 4.7,
        "images": [
            {
                "public_id": "products/vanilla_icecream",
                "url": "https://images.unsplash.com/photo-1580918451893-ecf4d9c79e6f?fit=crop&w=400&h=400&q=80"
            }
        ],
        "category": "Thực phẩm đông lạnh",
        "seller": "IceWorld",
        "stock": 150,
        "numOfReviews": 50,
        "reviews": []
    },
    {
        "name": "Nước Mắm Cá Cơm Truyền Thống (500ml)",
        "price": "65.00",
        "description": "Nước mắm nhỉ cốt cá cơm, hương vị đậm đà truyền thống.",
        "ratings": 4.9,
        "images": [
            {
                "public_id": "products/fish_sauce",
                "url": "https://images.unsplash.com/photo-1601662520637-2e1d7d0a6c0b?fit=crop&w=400&h=400&q=80"
            }
        ],
        "category": "Thực phẩm Khô - Gia Vị",
        "seller": "VietSpice",
        "stock": 400,
        "numOfReviews": 60,
        "reviews": []
    },
    {
        "name": "Bánh Quy Bơ Đan Mạch Hộp Thiếc (454g)",
        "price": "95.00",
        "description": "Bánh quy bơ cao cấp, thích hợp làm quà tặng hoặc ăn vặt.",
        "ratings": 4.4,
        "images": [
            {
                "public_id": "products/danish_butter_cookies",
                "url": "https://images.unsplash.com/photo-1594967396113-ec846c4f09d7?fit=crop&w=400&h=400&q=80"
            }
        ],
        "category": "Bánh kẹo - Đồ ăn vặt",
        "seller": "SweetHouse",
        "stock": 180,
        "numOfReviews": 30,
        "reviews": []
    },
    {
        "name": "Sữa Tươi Tiệt Trùng Không Đường (1 Lít)",
        "price": "35.50",
        "description": "Sữa tươi nguyên chất 100%, không đường, giàu canxi.",
        "ratings": 4.7,
        "images": [
            {
                "public_id": "products/fresh_milk",
                "url": "https://images.unsplash.com/photo-1554992759-b1d51a66e4a2?fit=crop&w=400&h=400&q=80"
            }
        ],
        "category": "Sữa - Sản phẩm từ sữa",
        "seller": "DairyFarm",
        "stock": 500,
        "numOfReviews": 80,
        "reviews": []
    },
    {
        "name": "Nước Ngọt Coca-Cola Zero Đường (Thùng 24 lon)",
        "price": "220.00",
        "description": "Coca-Cola không calo, không đường, giải khát tối đa.",
        "ratings": 4.6,
        "images": [
            {
                "public_id": "products/coca_cola_zero",
                "url": "https://images.unsplash.com/photo-1582572522770-5c6219080db1?fit=crop&w=400&h=400&q=80"
            }
        ],
        "category": "Đồ uống - Giải khát",
        "seller": "BevCorp",
        "stock": 350,
        "numOfReviews": 45,
        "reviews": []
    },
    {
        "name": "Sữa Tắm Dưỡng Ẩm Trắng Da Hương Hoa Hồng (1.2 Lít)",
        "price": "145.00",
        "description": "Sữa tắm với tinh chất hoa hồng, làm sạch sâu và dưỡng ẩm cho da mềm mịn.",
        "ratings": 4.8,
        "images": [
            {
                "public_id": "products/rose_shower_gel",
                "url": "https://images.unsplash.com/photo-1594470984180-87a748c5b96c?fit=crop&w=400&h=400&q=80"
            }
        ],
        "category": "Hóa Mỹ phẩm",
        "seller": "BeautyPlus",
        "stock": 250,
        "numOfReviews": 70,
        "reviews": []
    },
    {
        "name": "Kem Chống Nắng SPF 50+ PA++++",
        "price": "250.00",
        "description": "Bảo vệ da khỏi tia UVA/UVB cường độ cao, không gây nhờn rít.",
        "ratings": 4.9,
        "images": [
            {
                "public_id": "products/sunscreen_spf50",
                "url": "https://images.unsplash.com/photo-1582234033100-84c483d2581c?fit=crop&w=400&h=400&q=80"
            }
        ],
        "category": "Chăm sóc cá nhân",
        "seller": "SkinCare Pro",
        "stock": 190,
        "numOfReviews": 90,
        "reviews": []
    }
]